prepare_assignment/__init__.py
prepare_assignment/__main__.py
prepare_assignment/cli/__init__.py
prepare_assignment/cli/main.py
prepare_assignment/cli/task.py
prepare_assignment/cli/tasks.py
prepare_assignment/core/__init__.py
prepare_assignment/core/command.py
prepare_assignment/core/main.py
prepare_assignment/core/preparer.py
prepare_assignment/core/runner.py
prepare_assignment/core/subsituter.py
prepare_assignment/core/task_handler.py
prepare_assignment/core/validator.py
prepare_assignment/data/__init__.py
prepare_assignment/data/config.py
prepare_assignment/data/constants.py
prepare_assignment/data/errors.py
prepare_assignment/data/job_environment.py
prepare_assignment/data/prepare.py
prepare_assignment/data/task_definition.py
prepare_assignment/data/task_properties.py
prepare_assignment/schemas/config.schema.json
prepare_assignment/schemas/prepare.schema.json
prepare_assignment/schemas/task.schema.json
prepare_assignment/schemas/task.schema.json_template
prepare_assignment/utils/__init__.py
prepare_assignment/utils/config.py
prepare_assignment/utils/default_validator.py
prepare_assignment/utils/dependency.py
prepare_assignment/utils/executables.py
prepare_assignment/utils/logger.py
prepare_assignment/utils/paths.py
prepare_assignment/utils/tasks.py
prepare_assignment/utils/virtual_env.py
prepare_assignment/utils/yml_loader.py
prepare_assignment-0.2.1.dist-info/METADATA
prepare_assignment-0.2.1.dist-info/WHEEL
prepare_assignment-0.2.1.dist-info/entry_points.txt
prepare_assignment-0.2.1.dist-info/licenses/LICENSE
prepare_assignment-0.2.1.dist-info/RECORD
