Metadata-Version: 2.4
Name: prepare-assignment
Version: 0.2.1
Summary: Prepare assignment
License: MIT
License-File: LICENSE
Author: Bonajo
Author-email: m.bonajo@fontys.nl
Requires-Python: >=3.9,<4.0
Classifier: License :: OSI Approved :: MIT License
Classifier: Programming Language :: Python :: 3
Classifier: Programming Language :: Python :: 3.9
Classifier: Programming Language :: Python :: 3.10
Classifier: Programming Language :: Python :: 3.11
Classifier: Programming Language :: Python :: 3.12
Classifier: Programming Language :: Python :: 3.13
Classifier: Programming Language :: Python :: 3.14
Requires-Dist: dacite (>=1.9.2,<2.0.0)
Requires-Dist: gitpython (>=3.1.41,<4.0.0)
Requires-Dist: importlib-resources (>=6.1.1,<7.0.0)
Requires-Dist: jsonschema (>=4.21.1,<5.0.0)
Requires-Dist: multipledispatch (>=1.0.0,<2.0.0)
Requires-Dist: prepare-toolbox (==0.4.0)
Requires-Dist: ruamel-yaml (>=0.18.5,<0.19.0)
Requires-Dist: treelib (>=1.7.0,<2.0.0)
Requires-Dist: typer[all] (==0.17.3)
Requires-Dist: virtualenv (>=20.25.0,<21.0.0)
